elemental/__init__.py
elemental/actions.py
elemental/elemental.py
elemental/exceptions.py
elemental/getters.py
elemental/states.py
elemental/values.py
tests/__init__.py
tests/conftest.py
tests/test_attribute.py
tests/test_browser.py
tests/test_check.py
tests/test_click.py
tests/test_fill.py
tests/test_get_button.py
tests/test_get_element.py
tests/test_get_elements.py
tests/test_get_input.py
tests/test_get_parent.py
tests/test_html.py
tests/test_is_displayed.py
tests/test_is_enabled.py
tests/test_is_selected.py
tests/test_screenshot.py
tests/test_select.py
tests/test_text.py
tests/test_title.py
tests/test_uncheck.py
tests/test_url.py
tests/test_visit.py
tests/utilities.py
elemental-0.4.0.dist-info/LICENCE
elemental-0.4.0.dist-info/METADATA
elemental-0.4.0.dist-info/WHEEL
elemental-0.4.0.dist-info/top_level.txt
elemental-0.4.0.dist-info/RECORD
