Metadata-Version: 2.1
Name: elemental
Version: 0.4.0
Summary: Faster, easier and more robust Selenium automation.
Home-page: https://github.com/red-and-black/elemental
Author: Keira & Sky
Author-email: humans@redandblack.io
License: MIT
Keywords: selenium,testing
Platform: UNKNOWN
Classifier: Development Status :: 4 - Beta
Classifier: Intended Audience :: Developers
Classifier: License :: OSI Approved :: MIT License
Classifier: Operating System :: MacOS
Classifier: Operating System :: POSIX :: Linux
Classifier: Programming Language :: Python :: 3
Classifier: Programming Language :: Python :: 3.5
Classifier: Programming Language :: Python :: 3.6
Classifier: Programming Language :: Python :: 3.7
Classifier: Programming Language :: Python :: 3.8
Classifier: Programming Language :: Python :: 3.9
Classifier: Topic :: Internet :: WWW/HTTP :: Browsers
Classifier: Topic :: Software Development :: Testing
Requires-Python: >=3.5
Requires-Dist: selenium (>=3.141)
